{"nodes": [{"id": "backend_models_base_py", "label": "base.py", "file_type": "code", "source_file": "Backend/models/base.py", "source_location": "L1"}, {"id": "backend_models_base_basemodel", "label": "BaseModel", "file_type": "code", "source_file": "Backend/models/base.py", "source_location": "L12", "_callable": true}, {"id": "base", "label": "Base", "file_type": "code", "source_file": "", "source_location": ""}, {"id": "backend_models_base_timestampmixin", "label": "TimestampMixin", "file_type": "code", "source_file": "Backend/models/base.py", "source_location": "L27", "_callable": true}, {"id": "backend_models_base_rationale_13", "label": "Base model with common fields", "file_type": "rationale", "source_file": "Backend/models/base.py", "source_location": "L13"}, {"id": "backend_models_base_rationale_28", "label": "Mixin for created_at and updated_at", "file_type": "rationale", "source_file": "Backend/models/base.py", "source_location": "L28"}], "edges": [{"source": "backend_models_base_py", "target": "sqlalchemy", "relation": "imports_from", "context": "import", "confidence": "EXTRACTED", "source_file": "Backend/models/base.py", "source_location": "L2", "weight": 1.0}, {"source": "backend_models_base_py", "target": "sqlalchemy_types", "relation": "imports_from", "context": "import", "confidence": "EXTRACTED", "source_file": "Backend/models/base.py", "source_location": "L3", "weight": 1.0}, {"source": "backend_models_base_py", "target": "sqlalchemy_dialects_postgresql", "relation": "imports_from", "context": "import", "confidence": "EXTRACTED", "source_file": "Backend/models/base.py", "source_location": "L4", "weight": 1.0}, {"source": "backend_models_base_py", "target": "core_database", "relation": "imports_from", "context": "import", "confidence": "EXTRACTED", "source_file": "Backend/models/base.py", "source_location": "L5", "weight": 1.0}, {"source": "backend_models_base_py", "target": "uuid", "relation": "imports", "context": "import", "confidence": "EXTRACTED", "source_file": "Backend/models/base.py", "source_location": "L6", "weight": 1.0}, {"source": "backend_models_base_py", "target": "backend_models_base_basemodel", "relation": "contains", "confidence": "EXTRACTED", "source_file": "Backend/models/base.py", "source_location": "L12", "weight": 1.0}, {"source": "backend_models_base_basemodel", "target": "base", "relation": "inherits", "confidence": "EXTRACTED", "source_file": "Backend/models/base.py", "source_location": "L12", "weight": 1.0}, {"source": "backend_models_base_py", "target": "backend_models_base_timestampmixin", "relation": "contains", "confidence": "EXTRACTED", "source_file": "Backend/models/base.py", "source_location": "L27", "weight": 1.0}, {"source": "backend_models_base_rationale_13", "target": "backend_models_base_basemodel", "relation": "rationale_for", "confidence": "EXTRACTED", "source_file": "Backend/models/base.py", "source_location": "L13", "weight": 1.0}, {"source": "backend_models_base_rationale_28", "target": "backend_models_base_timestampmixin", "relation": "rationale_for", "confidence": "EXTRACTED", "source_file": "Backend/models/base.py", "source_location": "L28", "weight": 1.0}], "raw_calls": []}